human_risk_graph-0.1.3.dist-info/licenses/LICENSE
human_risk_graph-0.1.3.dist-info/licenses/NOTICE.md
src/__init__.py
src/cli.py
src/graph_analysis.py
src/hrg.py
src/metrics.py
src/reports.py
src/visualization.py
tests/__init__.py
tests/test_coverage.py
tests/test_graph_analysis.py
tests/test_hrg.py
tests/test_metrics.py
human_risk_graph-0.1.3.dist-info/METADATA
human_risk_graph-0.1.3.dist-info/WHEEL
human_risk_graph-0.1.3.dist-info/entry_points.txt
human_risk_graph-0.1.3.dist-info/top_level.txt
human_risk_graph-0.1.3.dist-info/RECORD
